wostools/__init__.py
wostools/_testutils.py
wostools/article.py
wostools/base.py
wostools/cached.py
wostools/cli.py
wostools/exceptions.py
wostools/fields.py
wostools/sources/__init__.py
wostools/sources/isi.py
wostools/sources/scopus.py
wostools-3.0.2.dist-info/AUTHORS.md
wostools-3.0.2.dist-info/LICENSE
wostools-3.0.2.dist-info/METADATA
wostools-3.0.2.dist-info/WHEEL
wostools-3.0.2.dist-info/entry_points.txt
wostools-3.0.2.dist-info/top_level.txt
wostools-3.0.2.dist-info/RECORD
