Metadata-Version: 2.1
Name: wostools
Version: 3.0.2
Summary: Translates isi web of knowledge files into python objects.
Home-page: https://github.com/coreofscience/python-wostools
Author: Core of Science
Author-email: dev@coreofscience.com
License: MIT license
Keywords: wostools
Platform: UNKNOWN
Classifier: Development Status :: 2 - Pre-Alpha
Classifier: Intended Audience :: Developers
Classifier: License :: OSI Approved :: MIT License
Classifier: Natural Language :: English
Classifier: Programming Language :: Python :: 3
Classifier: Programming Language :: Python :: 3.7
Classifier: Programming Language :: Python :: 3.8
Classifier: Programming Language :: Python :: 3.9
Requires-Dist: Click (>=7.0<8)
